sedb/__init__.py
sedb/bridger.py
sedb/elastic.py
sedb/elastic_filter.py
sedb/embed.py
sedb/faiss.py
sedb/faiss_server.py
sedb/llm.py
sedb/message.py
sedb/milvus.py
sedb/mongo.py
sedb/mongo_filter.py
sedb/mongo_generator.py
sedb/mongo_pipeline.py
sedb/mongo_types.py
sedb/qdrant.py
sedb/redis.py
sedb/rocks.py
sedb-1.3.1.dist-info/METADATA
sedb-1.3.1.dist-info/WHEEL
sedb-1.3.1.dist-info/top_level.txt
sedb-1.3.1.dist-info/RECORD
