Metadata-Version: 2.4
Name: sedb
Version: 1.3.1
Summary: Search Engine DataBase utils
Author: Hansimov
License-Expression: MIT
Project-URL: Homepage, https://github.com/Hansimov/sedb
Project-URL: Issues, https://github.com/Hansimov/sedb/issues
Classifier: Programming Language :: Python :: 3
Classifier: Operating System :: OS Independent
Requires-Python: >=3.6
Requires-Dist: tclogger
Provides-Extra: common
Requires-Dist: pymongo; extra == "common"
Requires-Dist: elasticsearch; extra == "common"
Requires-Dist: redis; extra == "common"
Requires-Dist: rocksdict; extra == "common"
Provides-Extra: vector
Requires-Dist: numpy; extra == "vector"
Requires-Dist: pymilvus; extra == "vector"
Requires-Dist: qdrant-client; extra == "vector"
Requires-Dist: faiss-cpu; extra == "vector"
Provides-Extra: all
Requires-Dist: pymongo; extra == "all"
Requires-Dist: elasticsearch; extra == "all"
Requires-Dist: redis; extra == "all"
Requires-Dist: rocksdict; extra == "all"
Requires-Dist: numpy; extra == "all"
Requires-Dist: pymilvus; extra == "all"
Requires-Dist: qdrant-client; extra == "all"
Requires-Dist: faiss-cpu; extra == "all"
Requires-Dist: requests; extra == "all"
Requires-Dist: pydantic; extra == "all"
Requires-Dist: fastapi; extra == "all"
Requires-Dist: uvicorn; extra == "all"
